awsgreengrasspubsubsdk/__init__.py
awsgreengrasspubsubsdk/message_formatter.py
awsgreengrasspubsubsdk/pubsub_client.py
awsgreengrasspubsubsdk/pubsub_ipc.py
awsgreengrasspubsubsdk/pubsub_mqtt.py
awsgreengrasspubsubsdk-0.1.5.dist-info/LICENSE
awsgreengrasspubsubsdk-0.1.5.dist-info/METADATA
awsgreengrasspubsubsdk-0.1.5.dist-info/WHEEL
awsgreengrasspubsubsdk-0.1.5.dist-info/top_level.txt
awsgreengrasspubsubsdk-0.1.5.dist-info/RECORD
