Metadata-Version: 2.1
Name: awsgreengrasspubsubsdk
Version: 0.1.5
Summary: AWS Greengrass IoT Pubsub SDK for Python
Home-page: https://github.com/awslabs/aws-greengrass-labs-iot-pubsub-sdk-for-python
Author: Dean Colcott
Author-email: dean.colcott@gmail.com
License: License :: OSI Approved :: MIT License
Classifier: Programming Language :: Python :: 3
Classifier: Intended Audience :: Developers
Classifier: License :: OSI Approved :: MIT License
Classifier: Operating System :: OS Independent
Requires-Python: >=3.6
License-File: LICENSE
Requires-Dist: awsiotsdk
